tmp/memory.v
module Memory(
    input load,wen,d_load,
    input wire [31:0] write_data,
    input wire [31:0] read_addr,write_addr,d_read_addr,
    output reg [31:0] out_data,d_out_data
);

    reg [7:0] m[0:65535];

    always @(negedge load) begin
        out_data <= {m[read_addr+3],m[read_addr+2],m[read_addr+1],m[read_addr]};
    end

    always @(negedge d_load) begin
        d_out_data <= {m[d_read_addr+3],m[d_read_addr+2],m[d_read_addr+1],m[d_read_addr]};
    end

    always @(negedge wen) begin
        m[write_addr] <= write_data[7:0];
        m[write_addr+1] <= write_data[15:8];
        m[write_addr+2] <= write_data[23:16];
        m[write_addr+3] <= write_data[31:24];
    end


endmodule

tmp/core.v
`include "consts.h"
`include "instruction.h"
`include "memory.v"

module Core(
    input rst,clk
);

    reg [2:0] stage;
    reg [31:0] pc;

    //Register
    reg [31:0] rs [0:31];
    reg [31:0] csr [0:4095];

    integer i;
    initial begin
        stage <= `IF;
        pc <= 32'b0;
        // for(i=0;i<32;i++) begin
            // rs[i] <= i;
        // end
        // for(i=0;i<4095;i++) begin
            // csr[i] <= i;
        // end
        //rs[0] = 32'b1;
    end

    reg [31:0] alu_out;

    //Memory
    reg memory_load,memory_wen,memory_d_load;
    reg [31:0] memory_write_addr;
    reg [31:0] memory_write_data;
    wire [31:0] memory_read_data,memory_d_read_data;
    Memory memory(
        .load(memory_load),
        .wen(memory_wen),
        .d_load(memory_d_load),
        .read_addr(pc),
        .d_read_addr(alu_out),
        .write_addr(alu_out),
        .write_data(memory_write_data),
        .out_data(memory_read_data),
        .d_out_data(memory_d_read_data)
    );
    initial begin
        memory_load <= `MEM_UNLOAD;
        memory_wen <= `MEM_UNWRITE;
        memory_d_load <= `MEM_UNLOAD;
        memory_write_addr <= 32'h0;
        memory_write_data <= 32'h0;
    end

    //Decoder
    wire [4:0] rs1_addr = memory_read_data[19:15]; 
    wire [4:0] rs2_addr = memory_read_data[24:20];
    wire [4:0] rd_addr = memory_read_data[11:7];
    wire [31:0] rs1,rs2;
    wire [11:0] imm_i = memory_read_data[31:20];
    wire [31:0] imm_i_sext = {{20{imm_i[11]}},imm_i};
    wire [11:0] imm_s = {memory_read_data[31:25],memory_read_data[11:7]};
    wire [31:0] imm_s_sext = {{20{imm_s[11]}},imm_s};
    wire[12:0] imm_b = {memory_read_data[31],memory_read_data[7],memory_read_data[30:25],memory_read_data[11:8],1'b0};
    wire [31:0] imm_b_sext = {{19{imm_b[12]}},imm_b};
    wire [20:0] imm_j = {memory_read_data[31],memory_read_data[19:12],memory_read_data[20],memory_read_data[30:21],{1'b0}};
    wire [31:0] imm_j_sext = {{11{imm_j[20]}},imm_j};
    wire [19:0] imm_u = memory_read_data[31:12];
    wire [31:0] imm_u_shifted_sext = {imm_u,{12'b0}};
    wire [19:0] csr_addr = memory_read_data[31:20];
    wire [4:0] imm_z = memory_read_data[19:15];
    wire [31:0] imm_z_uext = {27'b0,imm_z};

    always @(posedge clk) begin
        if((stage == `WB) || rst) begin
            stage <= `IF;
        end
        else begin
            stage <= stage + 1; 
        end
    end

    always @(*) begin
        casez(stage)
            `IF     :   Fetch();
            `ID     :   Decode();
            `EX     :   Execute();
            `MEM    :   MemoryAccess();
            `WB     :   WriteBack();
        endcase
        rs[0] <= 32'b0;
    end

    //Instruction Fetch
    reg inc_flag = 1'b0;
    reg [31:0] br_jmp = 32'b0;
    reg br_flag = 1'b0;
    reg [31:0] jmp = 32'b0;
    reg jmp_flag = 1'b0;
    task Fetch;
        begin
            if(inc_flag & !br_flag) begin
                pc <= pc + 4;
            end else if(br_flag) begin
                pc <= br_jmp;
                br_flag <= 1'b0;
            end
            if(jmp_flag) begin
                pc <= jmp; 
                jmp_flag <= 1'b0;
            end
            if(pc == 32'h0) begin
               inc_flag = 1'b1;
            end

            memory_load <= `MEM_LOAD;
            //1ps 
            #1 memory_load <= `MEM_UNLOAD;
        end
    endtask

    //Instruction Decode
    assign rs1 = rs[rs1_addr];
    assign rs2 = rs[rs2_addr];
    task Decode;
        begin
            
        end
    endtask

    //Execution
    
    task Execute;
        begin
            casez(memory_read_data)
                `LW     :   alu_out <= rs1 + imm_i_sext;
                `SW     :   alu_out <= rs1 + imm_s_sext;
                `ADD    :   alu_out <= rs1 + rs2;
                `SUB    :   alu_out <= rs1 - rs2;   
                `ADDI   :   alu_out <= rs1 + imm_i_sext;
                `AND    :   alu_out <= rs1 & rs2;
                `OR     :   alu_out <= rs1 | rs2;
                `XOR    :   alu_out <= rs1 ^ rs2;
                `ANDI   :   alu_out <= rs1 & imm_i_sext;
                `ORI    :   alu_out <= rs1 | imm_i_sext;
                `XORI   :   alu_out <= rs1 ^ imm_i_sext;
                `SLL    :   alu_out <= rs1 << rs2[4:0];
                `SRL    :   alu_out <= rs1 >> rs2[4:0];
                `SRA    :   alu_out <= $signed(rs1) >>> rs2[4:0];
                `SLLI   :   alu_out <= rs1 << imm_i_sext[4:0];
                `SRLI   :   alu_out <= rs1 >> imm_i_sext[4:0];
                `SRAI   :   alu_out <= $signed(rs1) >>> imm_i_sext[4:0];
                `SLT    :   alu_out <= {($signed(rs1) < $signed(rs2)) ? 32'b1 : 32'b0};
                `SLTU   :   alu_out <= {(rs1 < rs2) ? 32'b1 : 32'b0};
                `SLTI   :   alu_out <= {($signed(rs1) < $signed(imm_i_sext)) ? 32'b1 : 32'b0};
                `SLTIU  :   alu_out <= {(rs1 < imm_i_sext) ? 32'b1 : 32'b0};
                //ジャンプ命令のジャンプアドレス先計算って、命令フェッチ時のプログラムカウンタをベースにしたほうがいい？わからん
                //マルチサイクルなら問題ないけど、パイプライン実装したら命令フェッチ時のアドレスを逆算するだけでいいんかなしらんけど
                `BEQ    :   alu_out <= {(rs1 == rs2) ? (imm_b_sext + pc) : 32'b0};
                `BNE    :   alu_out <= {(rs1 != rs2) ? (imm_b_sext + pc) : 32'b0};
                `BLT    :   alu_out <= {($signed(rs1) < $signed(rs2)) ? (imm_b_sext + pc) : 32'b0};
                `BGE    :   alu_out <= {($signed(rs1) >= $signed(rs2)) ? (imm_b_sext + pc) : 32'b0};
                `BLTU   :   alu_out <= {(rs1 < rs2) ? (imm_b_sext + pc) : 32'b0};
                `BGEU   :   alu_out <= {(rs1 >= rs2) ? (imm_b_sext + pc) : 32'b0};
                `JAL    :   alu_out <= pc + imm_j_sext;
                `JALR   :   alu_out <= (rs[rs1_addr] + imm_i_sext) & (~32'b1);
                `LUI    :   alu_out <= imm_u_shifted_sext;
                `AUIPC  :   alu_out <= pc + imm_u_shifted_sext;
                //CSR命令のレジスタライトバックってCSRレジスタに書き込んだ後のデータなのか、書き込む前のデータなのかわからん
                //けど書き込み前のCSRレジスタのデータをライトバックしても意味ないから多分CSRに書き込むのが先なはず
                `CSRRW  :   alu_out <= rs[rs1_addr];
                `CSRRWI :   alu_out <= imm_z_uext;
                `CSRRS  :   alu_out <= csr[csr_addr] | rs[rs1_addr];
                `CSRRSI :   alu_out <= csr[csr_addr] | imm_z_uext;
                `CSRRC  :   alu_out <= csr[csr_addr] & (~rs[rs1_addr]);
                `CSRRCI :   alu_out <= csr[csr_addr] & (~imm_z_uext);
            endcase
        end
    endtask

    //Memory Access
    task MemoryAccess;
        begin
            casez(memory_read_data)
                `LW    :   
                    begin
                        memory_d_load <= `MEM_LOAD;
                    end
                `SW     :
                    begin
                        memory_write_data <= rs2;
                        memory_wen <= `MEM_WRITE;
                    end
                `CSRRW,`CSRRWI,`CSRRS,`CSRRSI,`CSRRC,`CSRRCI    :
                    begin
                        csr[csr_addr] <= alu_out;
                    end
                `ECALL      :
                    begin
                        csr[12'h342] <= 32'd11;
                    end    
            endcase
            #1 memory_d_load <= `MEM_UNLOAD;
            #1 memory_wen <= `MEM_UNWRITE;
        end
    endtask

    //Write Back
    task WriteBack;
        begin
            casez(memory_read_data)
                `LW     :   rs[rd_addr] <= memory_d_read_data;
                `ADD,`SUB,`ADDI,`AND,`OR,`XOR,`ANDI,`ORI,`XORI,`SLL,`SRL,`SRA,`SLLI,`SRLI,`SRAI,`SLT,`SLTU,`SLTI,`SLTIU   :
                    begin
                        rs[rd_addr] <= alu_out;
                    end
                `BEQ,`BNE,`BLT,`BGE,`BLTU,`BGEU    :
                    begin
                        if(alu_out != 32'b0) begin
                            br_flag <= 1'b1;
                            br_jmp <= alu_out;
                        end
                    end
                `JAL,`JALR    :
                    begin
                        jmp_flag <= 1'b1;
                        jmp <= alu_out;
                        rs[rd_addr] <= pc + 32'd4;
                    end
                `LUI,`AUIPC    :
                    begin
                        rs[rd_addr] <= alu_out;
                    end
                `CSRRW,`CSRRWI,`CSRRS,`CSRRSI,`CSRRC,`CSRRCI    :
                    begin
                        rs[rd_addr] <= csr[csr_addr];
                    end
                `ECALL      :
                    begin
                        jmp_flag <= 1'b1;
                        jmp <= csr[12'h305];
                    end
            endcase
        end
    endtask

endmodule

tmp/rv32si-p-scall.v
`timescale 1ns/1ps
`include "core.v"
  
module startup;

    parameter step = 10;
    parameter ticks = 5000;
    parameter memory_hex = "build/riscv-tests-hex/rv32si-p-scall.hex";
    parameter result_file_path = "result/rv32si-p-scall.txt";

    reg clk;
    reg rst;

    Core core(
        .clk(clk),
        .rst(rst)
        );
    initial begin
        $readmemh(memory_hex,core.memory.m,16'h0,16'hffff);
        //$readmemh("mem.hex",core.memory.m,16'h0,16'hffff);
    end

    integer i;
    initial
        begin
            $dumpfile("vcd/rv32si-p-scall.vcd");
            $dumpvars(0,core);
            for(i=0;i<32;i++) begin
               $dumpvars(1,core.memory.m[i]);
            end
            for(i=0;i<31;i++) begin
                $dumpvars(2,core.rs[i]);
            end
            for(i=0;i<31;i++) begin
                $dumpvars(3,core.csr[i]);
            end
        end

    initial
        begin
            clk = 1'b1;
            forever
                begin
                    #(step/2) clk = !clk;
                end
        end

    initial
        begin
            rst = 1'b0;
            repeat (1) @(posedge clk) rst <= 1'b1;
            @(posedge clk) rst <= 1'b0;
        end

    integer fp;

    initial
       begin
           repeat (ticks) begin
                @(posedge clk);
                if(core.pc == 32'h44) begin
                    fp = $fopen(result_file_path);
                    if(core.rs[3] == 32'b1) begin
                        $fdisplay(fp,"passed");
                    end else begin
                        $fdisplay(fp,"failed");
                    end
                    $fclose(fp);
                    $finish;
                end
           end
           $finish;
       end

endmodule

tmp/vcd/rv32ui-p-jal.vcd
$date
	Sat Aug 12 00:21:07 2023
$end
$version
	Icarus Verilog
$end
$timescale
	1ps
$end
$scope module startup $end
$scope module core $end
$var wire 1 ! clk $end
$var wire 32 " rs1 [31:0] $end
$var wire 32 # rs2 [31:0] $end
$var wire 1 $ rst $end
$var wire 5 % rs2_addr [4:0] $end
$var wire 5 & rs1_addr [4:0] $end
$var wire 5 ' rd_addr [4:0] $end
$var wire 32 ( memory_read_data [31:0] $end
$var wire 32 ) memory_d_read_data [31:0] $end
$var wire 32 * imm_z_uext [31:0] $end
$var wire 5 + imm_z [4:0] $end
$var wire 32 , imm_u_shifted_sext [31:0] $end
$var wire 20 - imm_u [19:0] $end
$var wire 32 . imm_s_sext [31:0] $end
$var wire 12 / imm_s [11:0] $end
$var wire 32 0 imm_j_sext [31:0] $end
$var wire 21 1 imm_j [20:0] $end
$var wire 32 2 imm_i_sext [31:0] $end
$var wire 12 3 imm_i [11:0] $end
$var wire 32 4 imm_b_sext [31:0] $end
$var wire 13 5 imm_b [12:0] $end
$var wire 20 6 csr_addr [19:0] $end
$var reg 32 7 alu_out [31:0] $end
$var reg 1 8 br_flag $end
$var reg 32 9 br_jmp [31:0] $end
$var reg 1 : inc_flag $end
$var reg 32 ; jmp [31:0] $end
$var reg 1 < jmp_flag $end
$var reg 1 = memory_d_load $end
$var reg 1 > memory_load $end
$var reg 1 ? memory_wen $end
$var reg 32 @ memory_write_addr [31:0] $end
$var reg 32 A memory_write_data [31:0] $end
$var reg 32 B pc [31:0] $end
$var reg 3 C stage [2:0] $end
$scope module memory $end
$var wire 1 = d_load $end
$var wire 32 D d_read_addr [31:0] $end
$var wire 1 > load $end
$var wire 32 E read_addr [31:0] $end
$var wire 1 ? wen $end
$var wire 32 F write_addr [31:0] $end
$var wire 32 G write_data [31:0] $end
$var reg 32 H d_out_data [31:0] $end
$var reg 32 I out_data [31:0] $end
$upscope $end
$scope task Decode $end
$upscope $end
$scope task Execute $end
$upscope $end
$scope task Fetch $end
$upscope $end
$scope task MemoryAccess $end
$upscope $end
$scope task WriteBack $end
$upscope $end
$upscope $end
$upscope $end
$scope module startup $end
$scope module core $end
$scope module memory $end
$var reg 8 J \m[0] [7:0] $end
$upscope $end
$upscope $end
$upscope $end
$scope module startup $end
$scope module core $end
$scope module memory $end
$var reg 8 K \m[1] [7:0] $end
$upscope $end
$upscope $end
$upscope $end
$scope module startup $end
$scope module core $end
$scope module memory $end
$var reg 8 L \m[2] [7:0] $end
$upscope $end
$upscope $end
$upscope $end
$scope module startup $end
$scope module core $end
$scope module memory $end
$var reg 8 M \m[3] [7:0] $end
$upscope $end
$upscope $end
$upscope $end
$scope module startup $end
$scope module core $end
$scope module memory $end
$var reg 8 N \m[4] [7:0] $end
$upscope $end
$upscope $end
$upscope $end
$scope module startup $end
$scope module core $end
$scope module memory $end
$var reg 8 O \m[5] [7:0] $end
$upscope $end
$upscope $end
$upscope $end
$scope module startup $end
$scope module core $end
$scope module memory $end
$var reg 8 P \m[6] [7:0] $end
$upscope $end
$upscope $end
$upscope $end
$scope module startup $end
$scope module core $end
$scope module memory $end
$var reg 8 Q \m[7] [7:0] $end
$upscope $end
$upscope $end
$upscope $end
$scope module startup $end
$scope module core $end
$scope module memory $end
$var reg 8 R \m[8] [7:0] $end
$upscope $end
$upscope $end
$upscope $end
$scope module startup $end
$scope module core $end
$scope module memory $end
$var reg 8 S \m[9] [7:0] $end
$upscope $end
$upscope $end
$upscope $end
$scope module startup $end
$scope module core $end
$scope module memory $end
$var reg 8 T \m[10] [7:0] $end
$upscope $end
$upscope $end
$upscope $end
$scope module startup $end
$scope module core $end
$scope module memory $end
$var reg 8 U \m[11] [7:0] $end
$upscope $end
$upscope $end
$upscope $end
$scope module startup $end
$scope module core $end
$scope module memory $end
$var reg 8 V \m[12] [7:0] $end
$upscope $end
$upscope $end
$upscope $end
$scope module startup $end
$scope module core $end
$scope module memory $end
$var reg 8 W \m[13] [7:0] $end
$upscope $end
$upscope $end
$upscope $end
$scope module startup $end
$scope module core $end
$scope module memory $end
$var reg 8 X \m[14] [7:0] $end
$upscope $end
$upscope $end
$upscope $end
$scope module startup $end
$scope module core $end
$scope module memory $end
$var reg 8 Y \m[15] [7:0] $end
$upscope $end
$upscope $end
$upscope $end
$scope module startup $end
$scope module core $end
$scope module memory $end
$var reg 8 Z \m[16] [7:0] $end
$upscope $end
$upscope $end
$upscope $end
$scope module startup $end
$scope module core $end
$scope module memory $end
$var reg 8 [ \m[17] [7:0] $end
$upscope $end
$upscope $end
$upscope $end
$scope module startup $end
$scope module core $end
$scope module memory $end
$var reg 8 \ \m[18] [7:0] $end
$upscope $end
$upscope $end
$upscope $end
$scope module startup $end
$scope module core $end
$scope module memory $end
$var reg 8 ] \m[19] [7:0] $end
$upscope $end
$upscope $end
$upscope $end
$scope module startup $end
$scope module core $end
$scope module memory $end
$var reg 8 ^ \m[20] [7:0] $end
$upscope $end
$upscope $end
$upscope $end
$scope module startup $end
$scope module core $end
$scope module memory $end
$var reg 8 _ \m[21] [7:0] $end
$upscope $end
$upscope $end
$upscope $end
$scope module startup $end
$scope module core $end
$scope module memory $end
$var reg 8 ` \m[22] [7:0] $end
$upscope $end
$upscope $end
$upscope $end
$scope module startup $end
$scope module core $end
$scope module memory $end
$var reg 8 a \m[23] [7:0] $end
$upscope $end
$upscope $end
$upscope $end
$scope module startup $end
$scope module core $end
$scope module memory $end
$var reg 8 b \m[24] [7:0] $end
$upscope $end
$upscope $end
$upscope $end
$scope module startup $end
$scope module core $end
$scope module memory $end
$var reg 8 c \m[25] [7:0] $end
$upscope $end
$upscope $end
$upscope $end
$scope module startup $end
$scope module core $end
$scope module memory $end
$var reg 8 d \m[26] [7:0] $end
$upscope $end
$upscope $end
$upscope $end
$scope module startup $end
$scope module core $end
$scope module memory $end
$var reg 8 e \m[27] [7:0] $end
$upscope $end
$upscope $end
$upscope $end
$scope module startup $end
$scope module core $end
$scope module memory $end
$var reg 8 f \m[28] [7:0] $end
$upscope $end
$upscope $end
$upscope $end
$scope module startup $end
$scope module core $end
$scope module memory $end
$var reg 8 g \m[29] [7:0] $end
$upscope $end
$upscope $end
$upscope $end
$scope module startup $end
$scope module core $end
$scope module memory $end
$var reg 8 h \m[30] [7:0] $end
$upscope $end
$upscope $end
$upscope $end
$scope module startup $end
$scope module core $end
$scope module memory $end
$var reg 8 i \m[31] [7:0] $end
$upscope $end
$upscope $end
$upscope $end
$scope module startup $end
$scope module core $end
$var reg 32 j \rs[0] [31:0] $end
$upscope $end
$upscope $end
$scope module startup $end
$scope module core $end
$var reg 32 k \rs[1] [31:0] $end
$upscope $end
$upscope $end
$scope module startup $end
$scope module core $end
$var reg 32 l \rs[2] [31:0] $end
$upscope $end
$upscope $end
$scope module startup $end
$scope module core $end
$var reg 32 m \rs[3] [31:0] $end
$upscope $end
$upscope $end
$scope module startup $end
$scope module core $end
$var reg 32 n \rs[4] [31:0] $end
$upscope $end
$upscope $end
$scope module startup $end
$scope module core $end
$var reg 32 o \rs[5] [31:0] $end
$upscope $end
$upscope $end
$scope module startup $end
$scope module core $end
$var reg 32 p \rs[6] [31:0] $end
$upscope $end
$upscope $end
$scope module startup $end
$scope module core $end
$var reg 32 q \rs[7] [31:0] $end
$upscope $end
$upscope $end
$scope module startup $end
$scope module core $end
$var reg 32 r \rs[8] [31:0] $end
$upscope $end
$upscope $end
$scope module startup $end
$scope module core $end
$var reg 32 s \rs[9] [31:0] $end
$upscope $end
$upscope $end
$scope module startup $end
$scope module core $end
$var reg 32 t \rs[10] [31:0] $end
$upscope $end
$upscope $end
$scope module startup $end
$scope module core $end
$var reg 32 u \rs[11] [31:0] $end
$upscope $end
$upscope $end
$scope module startup $end
$scope module core $end
$var reg 32 v \rs[12] [31:0] $end
$upscope $end
$upscope $end
$scope module startup $end
$scope module core $end
$var reg 32 w \rs[13] [31:0] $end
$upscope $end
$upscope $end
$scope module startup $end
$scope module core $end
$var reg 32 x \rs[14] [31:0] $end
$upscope $end
$upscope $end
$scope module startup $end
$scope module core $end
$var reg 32 y \rs[15] [31:0] $end
$upscope $end
$upscope $end
$scope module startup $end
$scope module core $end
$var reg 32 z \rs[16] [31:0] $end
$upscope $end
$upscope $end
$scope module startup $end
$scope module core $end
$var reg 32 { \rs[17] [31:0] $end
$upscope $end
$upscope $end
$scope module startup $end
$scope module core $end
$var reg 32 | \rs[18] [31:0] $end
$upscope $end
$upscope $end
$scope module startup $end
$scope module core $end
$var reg 32 } \rs[19] [31:0] $end
$upscope $end
$upscope $end
$scope module startup $end
$scope module core $end
$var reg 32 ~ \rs[20] [31:0] $end
$upscope $end
$upscope $end
$scope module startup $end
$scope module core $end
$var reg 32 !" \rs[21] [31:0] $end
$upscope $end
$upscope $end
$scope module startup $end
$scope module core $end
$var reg 32 "" \rs[22] [31:0] $end
$upscope $end
$upscope $end
$scope module startup $end
$scope module core $end
$var reg 32 #" \rs[23] [31:0] $end
$upscope $end
$upscope $end
$scope module startup $end
$scope module core $end
$var reg 32 $" \rs[24] [31:0] $end
$upscope $end
$upscope $end
$scope module startup $end
$scope module core $end
$var reg 32 %" \rs[25] [31:0] $end
$upscope $end
$upscope $end
$scope module startup $end
$scope module core $end
$var reg 32 &" \rs[26] [31:0] $end
$upscope $end
$upscope $end
$scope module startup $end
$scope module core $end
$var reg 32 '" \rs[27] [31:0] $end
$upscope $end
$upscope $end
$scope module startup $end
$scope module core $end
$var reg 32 (" \rs[28] [31:0] $end
$upscope $end
$upscope $end
$scope module startup $end
$scope module core $end
$var reg 32 )" \rs[29] [31:0] $end
$upscope $end
$upscope $end
$scope module startup $end
$scope module core $end
$var reg 32 *" \rs[30] [31:0] $end
$upscope $end
$upscope $end
$scope module startup $end
$scope module core $end
$var reg 32 +" \csr[0] [31:0] $end
$upscope $end
$upscope $end
$scope module startup $end
$scope module core $end
$var reg 32 ," \csr[1] [31:0] $end
$upscope $end
$upscope $end
$scope module startup $end
$scope module core $end
$var reg 32 -" \csr[2] [31:0] $end
$upscope $end
$upscope $end
$scope module startup $end
$scope module core $end
$var reg 32 ." \csr[3] [31:0] $end
$upscope $end
$upscope $end
$scope module startup $end
$scope module core $end
$var reg 32 /" \csr[4] [31:0] $end
$upscope $end
$upscope $end
$scope module startup $end
$scope module core $end
$var reg 32 0" \csr[5] [31:0] $end
$upscope $end
$upscope $end
$scope module startup $end
$scope module core $end
$var reg 32 1" \csr[6] [31:0] $end
$upscope $end
$upscope $end
$scope module startup $end
$scope module core $end
$var reg 32 2" \csr[7] [31:0] $end
$upscope $end
$upscope $end
$scope module startup $end
$scope module core $end
$var reg 32 3" \csr[8] [31:0] $end
$upscope $end
$upscope $end
$scope module startup $end
$scope module core $end
$var reg 32 4" \csr[9] [31:0] $end
$upscope $end
$upscope $end
$scope module startup $end
$scope module core $end
$var reg 32 5" \csr[10] [31:0] $end
$upscope $end
$upscope $end
$scope module startup $end
$scope module core $end
$var reg 32 6" \csr[11] [31:0] $end
$upscope $end
$upscope $end
$scope module startup $end
$scope module core $end
$var reg 32 7" \csr[12] [31:0] $end
$upscope $end
$upscope $end
$scope module startup $end
$scope module core $end
$var reg 32 8" \csr[13] [31:0] $end
$upscope $end
$upscope $end
$scope module startup $end
$scope module core $end
$var reg 32 9" \csr[14] [31:0] $end
$upscope $end
$upscope $end
$scope module startup $end
$scope module core $end
$var reg 32 :" \csr[15] [31:0] $end
$upscope $end
$upscope $end
$scope module startup $end
$scope module core $end
$var reg 32 ;" \csr[16] [31:0] $end
$upscope $end
$upscope $end
$scope module startup $end
$scope module core $end
$var reg 32 <" \csr[17] [31:0] $end
$upscope $end
$upscope $end
$scope module startup $end
$scope module core $end
$var reg 32 =" \csr[18] [31:0] $end
$upscope $end
$upscope $end
$scope module startup $end
$scope module core $end
$var reg 32 >" \csr[19] [31:0] $end
$upscope $end
$upscope $end
$scope module startup $end
$scope module core $end
$var reg 32 ?" \csr[20] [31:0] $end
$upscope $end
$upscope $end
$scope module startup $end
$scope module core $end
$var reg 32 @" \csr[21] [31:0] $end
$upscope $end
$upscope $end
$scope module startup $end
$scope module core $end
$var reg 32 A" \csr[22] [31:0] $end
$upscope $end
$upscope $end
$scope module startup $end
$scope module core $end
$var reg 32 B" \csr[23] [31:0] $end
$upscope $end
$upscope $end
$scope module startup $end
$scope module core $end
$var reg 32 C" \csr[24] [31:0] $end
$upscope $end
$upscope $end
$scope module startup $end
$scope module core $end
$var reg 32 D" \csr[25] [31:0] $end
$upscope $end
$upscope $end
$scope module startup $end
$scope module core $end
$var reg 32 E" \csr[26] [31:0] $end
$upscope $end
$upscope $end
$scope module startup $end
$scope module core $end
$var reg 32 F" \csr[27] [31:0] $end
$upscope $end
$upscope $end
$scope module startup $end
$scope module core $end
$var reg 32 G" \csr[28] [31:0] $end
$upscope $end
$upscope $end
$scope module startup $end
$scope module core $end
$var reg 32 H" \csr[29] [31:0] $end
$upscope $end
$upscope $end
$scope module startup $end
$scope module core $end
$var reg 32 I" \csr[30] [31:0] $end
$upscope $end
$upscope $end
$enddefinitions $end
#0
$dumpvars
bx I"
bx H"
bx G"
bx F"
bx E"
bx D"
bx C"
bx B"
bx A"
bx @"
bx ?"
bx >"
bx ="
bx <"
bx ;"
bx :"
bx 9"
bx 8"
bx 7"
bx 6"
bx 5"
bx 4"
bx 3"
bx 2"
bx 1"
bx 0"
bx /"
bx ."
bx -"
bx ,"
bx +"
bx *"
bx )"
bx ("
bx '"
bx &"
bx %"
bx $"
bx #"
bx ""
bx !"
bx ~
bx }
bx |
bx {
bx z
bx y
bx x
bx w
bx v
bx u
bx t
bx s
bx r
bx q
bx p
bx o
bx n
bx m
bx l
bx k
b0 j
b11 i
b11111111 h
b0 g
b1100011 f
b0 e
b10110000 d
b1111 c
b10010011 b
b11 a
b11111111 `
b100 _
b1100011 ^
b0 ]
b10010000 \
b1111 [
b10010011 Z
b11 Y
b11111111 X
b1000 W
b1100011 V
b0 U
b10000000 T
b1111 S
b10010011 R
b110100 Q
b100000 P
b101111 O
b1110011 N
b100 M
b10000000 L
b0 K
b1101111 J
bx I
bx H
b0 G
bx F
b0 E
bx D
bx C
b0 B
b0 A
b0 @
1?
1>
1=
0<
b0 ;
0:
b0 9
08
bx 7
b0xxxxxxxxxxxx 6
bx0 5
bx0 4
bx 3
bx 2
bx0 1
bx0 0
bx /
bx .
bx -
bx000000000000 ,
bx +
b0xxxxx *
bx )
bx (
bx '
bx &
bx %
0$
bx #
bx "
1!
$end
#5000
0!
#10000
1$
1!
#15000
0!
#20000
b0 *
b0 +
b1001000 6
b100100000000000000000000000 ,
b100100000000000 -
b1001000 0
b1001000 1
b1000000 4
b1000000 5
b1000000 .
b1000000 /
b1001000 2
b1001000 3
b0 '
b1000 %
b0 "
b0 &
b100100000000000000001101111 (
b100100000000000000001101111 I
0>
1:
b0 C
0$
1!
#21000
b0 j
1>
#25000
0!
#30000
b0 j
b1 C
1!
#35000
0!
#40000
b0 j
b1001000 7
b1001000 D
b1001000 F
b10 C
1!
#45000
0!
#50000
b11 C
1!
#52000
b0 j
#55000
0!
#60000
b0 j
b0 "
b1001000 ;
1<
b100 C
1!
#65000
0!
#70000
b0 6
b0 ,
b0 -
b0 0
b0 1
b100000000000 4
b100000000000 5
b1 .
b1 /
b0 2
b0 3
b1 '
b0 #
b0 %
b10010011 (
b10010011 I
0>
0<
b1001000 B
b1001000 E
b0 C
1!
#71000
b0 j
1>
#75000
0!
#80000
b0 j
b1 C
1!
#85000
0!
#90000
b0 j
b0 7
b0 D
b0 F
b10 C
1!
#95000
0!
#100000
b11 C
1!
#102000
b0 j
#105000
0!
#110000
b0 j
b0 k
b100 C
1!
#115000
0!
#120000
b10 4
b10 5
b10 .
b10 /
b10 '
b100010011 (
b100010011 I
0>
b1001100 B
b1001100 E
b0 C
1!
#121000
b0 j
1>
#125000
0!
#130000
b0 j
b1 C
1!
#135000
0!
#140000
b0 j
b10 C
1!
#145000
0!
#150000
b11 C
1!
#152000
b0 j
#155000
0!
#160000
b0 j
b0 l
b100 C
1!
#165000
0!
#170000
b100000000010 4
b100000000010 5
b11 .
b11 /
b11 '
b110010011 (
b110010011 I
0>
b1010000 B
b1010000 E
b0 C
1!
#171000
b0 j
1>
#175000
0!
#180000
b0 j
b1 C
1!
#185000
0!
#190000
b0 j
b10 C
1!
#195000
0!
#200000
b11 C
1!
#202000
b0 j
#205000
0!
#210000
b0 j
b0 m
b100 C
1!
#215000
0!
#220000
b100 4
b100 5
b100 .
b100 /
b100 '
b1000010011 (
b1000010011 I
0>
b1010100 B
b1010100 E
b0 C
1!
#221000
b0 j
1>
#225000
0!
#230000
b0 j
b1 C
1!
#235000
0!
#240000
b0 j
b10 C
1!
#245000
0!
#250000
b11 C
1!
#252000
b0 j
#255000
0!
#260000
b0 j
b0 n
b100 C
1!
#265000
0!
#270000
b100000000100 4
b100000000100 5
b101 .
b101 /
b101 '
b1010010011 (
b1010010011 I
0>
b1011000 B
b1011000 E
b0 C
1!
#271000
b0 j
1>
#275000
0!
#280000
b0 j
b1 C
1!
#285000
0!
#290000
b0 j
b10 C
1!
#295000
0!
#300000
b11 C
1!
#302000
b0 j
#305000
0!
#310000
b0 j
b0 o
b100 C
1!
#315000
0!
#320000
b110 4
b110 5
b110 .
b110 /
b110 '
b1100010011 (
b1100010011 I
0>
b1011100 B
b1011100 E
b0 C
1!
#321000
b0 j
1>
#325000
0!
#330000
b0 j
b1 C
1!
#335000
0!
#340000
b0 j
b10 C
1!
#345000
0!
#350000
b11 C
1!
#352000
b0 j
#355000
0!
#360000
b0 j
b0 p
b100 C
1!
#365000
0!
#370000
b100000000110 4
b100000000110 5
b111 .
b111 /
b111 '
b1110010011 (
b1110010011 I
0>
b1100000 B
b1100000 E
b0 C
1!
#371000
b0 j
1>
#375000
0!
#380000
b0 j
b1 C
1!
#385000
0!
#390000
b0 j
b10 C
1!
#395000
0!
#400000
b11 C
1!
#402000
b0 j
#405000
0!
#410000
b0 j
b0 q
b100 C
1!
#415000
0!
#420000
b1000 4
b1000 5
b1000 .
b1000 /
b1000 '
b10000010011 (
b10000010011 I
0>
b1100100 B
b1100100 E
b0 C
1!
#421000
b0 j
1>
#425000
0!
#430000
b0 j
b1 C
1!
#435000
0!
#440000
b0 j
b10 C
1!
#445000
0!
#450000
b11 C
1!
#452000
b0 j
#455000
0!
#460000
b0 j
b0 r
b100 C
1!
#465000
0!
#470000
b100000001000 4
b100000001000 5
b1001 .
b1001 /
b1001 '
b10010010011 (
b10010010011 I
0>
b1101000 B
b1101000 E
b0 C
1!
#471000
b0 j
1>
#475000
0!
#480000
b0 j
b1 C
1!
#485000
0!
#490000
b0 j
b10 C
1!
#495000
0!
#500000
b11 C
1!
#502000
b0 j
#505000
0!
#510000
b0 j
b0 s
b100 C
1!
#515000
0!
#520000
b1010 4
b1010 5
b1010 .
b1010 /
b1010 '
b10100010011 (
b10100010011 I
0>
b1101100 B
b1101100 E
b0 C
1!
#521000
b0 j
1>
#525000
0!
#530000
b0 j
b1 C
1!
#535000
0!
#540000
b0 j
b10 C
1!
#545000
0!
#550000
b11 C
1!
#552000
b0 j
#555000
0!
#560000
b0 j
b0 t
b100 C
1!
#565000
0!
#570000
b100000001010 4
b100000001010 5
b1011 .
b1011 /
b1011 '
b10110010011 (
b10110010011 I
0>
b1110000 B
b1110000 E
b0 C
1!
#571000
b0 j
1>
#575000
0!
