src/module/memory.v
module Memory(
        input load,
        input d_load,
        input wen,
        //for intruction fetch
        input wire[31:0] addr,
        input wire[31:0] w_data,
        //for data access
        input wire[31:0] d_addr,
        output reg[31:0] data,d_data
    );

    reg [7:0] m[0:65535];

    always @(negedge load) begin
        data <= {m[addr+3],m[addr+2],m[addr+1],m[addr]};
    end

    always @(negedge d_load) begin
        d_data <= {m[d_addr+3],m[d_addr+2],m[d_addr+1],m[d_addr]};
    end

    always @(negedge wen) begin
        $monitor("en");
        m[d_addr] <= w_data[7:0];
        m[d_addr+1] <= w_data[15:8];
        m[d_addr+2] <= w_data[23:16];
        m[d_addr+3] <= w_data[31:24];
    end
    
    initial begin
        //パスが間違っているように見えるが、実際の参照はトップレベルのモジュールからなのであってる。Makefile構成にしたら沼りそう
        $readmemh("module/add_test.hex",core.memory.m,16'h0,16'hffff);
    end

endmodule

src/cpu/core.v
`include "../inc/consts.h"
`include "../inc/instruction.h"
`include "module/memory.v"

module Core(
    input clk,
    input rst
    );
    
    //internal bus
    reg [31:0] pc;
    reg [2:0] stage;
    reg [31:0] inst;

    //Memory 
    reg [31:0] w_data;
    reg [0:0] wen;
    reg [0:0] d_load;
    wire [31:0] mem_data;
    wire [31:0] d_mem_data;
    reg [0:0] load;
    reg [31:0] addr;
    reg [31:0] d_addr;

    //Register
    reg [31:0] register [31:0];

    //Decoder
    reg [4:0] rs1_addr;
    reg [4:0] rs2_addr;
    reg [4:0] rd_addr;
    reg [12:0] imm_i;
    reg [12:0] imm_s;
    reg [31:0] imm_s_sext;
    reg [31:0] imm_i_sext;
    reg [31:0] rs1;
    reg [31:0] rs2;
    reg [31:0] rd;

    //ALU
    reg [31:0] alu_out;

    integer i;
    initial begin
        inst <= 32'd0;
        addr <= 32'd0;
        stage <= 2'd0;
        load <= 1'd1;
        d_load <= 1'd1;
        w_data <= 32'd0;
        rs1_addr <= 5'd0;
        rs2_addr <= 5'd0;
        rd_addr <= 5'd0;
        wen <= 1'd1;
        for(i=0;i<32;i++) begin
            register[i] <= i;
        end
    end

    Memory memory(
        .load(load),
        .d_load(d_load),
        .addr(addr),
        .d_addr(d_addr),
        .data(mem_data),
        .d_data(d_mem_data),
        .w_data(w_data),
        .wen(wen)
    );

    always @(posedge clk) begin
            if(rst) begin
                stage <= `IF;
            end else begin
                if(stage == `WB) begin
                    stage <= `IF;
                end else begin
                    stage <= stage + 1;
                end
            end
        end

    always @(posedge clk) begin
            if(rst) begin
                pc <= 0;
            end else begin
                casez(stage)
                    `IF     :   IntructionFetch();
                    `ID     :   IntructionDecode();
                    `EX     :   Excution();
                    `MEM    :   MemoryAccess();
                    `WB     :   WriteBack();
                endcase
            end
        end

    task IntructionFetch;
        begin
            pc <= pc + 4;
            addr <= pc;
            //load memory enable
            load <= 1'b0;
        end
    endtask

    task IntructionDecode;
        begin
            inst <= mem_data;
            //load memory disable
            load <= 1'b1;
            //for debug
            rs1_addr <= mem_data[19:15];
            rs2_addr <= mem_data[24:20];
            rd_addr <= mem_data[11:7];
            imm_i <= mem_data[31:20];
            imm_s <= {{mem_data[31:25]},{mem_data[11:7]}};
            //sign extension
            //{} -> materialization?
            imm_i_sext <= {{20{mem_data[31]}},mem_data[31:20]};
            imm_s_sext <= {{20{mem_data[31]}},{mem_data[31:25],mem_data[11:7]}};
            //direct load
            rs1 <= register[mem_data[19:15]];
            rs2 <= register[mem_data[24:20]];
            rd <=  register[mem_data[11:7]];
        end
    endtask

    task Excution;
    begin
        casez(inst)
            `LW     :   alu_out <= {rs1 + imm_i_sext};
            `SW     :   alu_out <= {rs1 + imm_s_sext};
            `ADD    :   alu_out <= {rs1 + rs2};
            `SUB    :   alu_out <= {rs1 - rs2};
            `ADDI   :   alu_out <= {rs1 + imm_i_sext};
            `AND    :   alu_out <= {rs1 & rs2};
            `OR     :   alu_out <= {rs1 | rs2};
            `XOR    :   alu_out <= {rs1 ^ rs2};
            `ANDI   :   alu_out <= {rs1 & imm_i_sext};
            `ORI    :   alu_out <= {rs1 | imm_i_sext};
            `XORI   :   alu_out <= {rs1 ^ imm_i_sext};
        endcase
    end
    endtask

    task MemoryAccess;
    begin
        casez(inst)
            `LW     :   
                begin 
                    d_addr <= alu_out;
                    d_load <= 1'b0;
                end
            `SW     :
                begin
                    d_addr <= alu_out;
                    wen <= 1'b0;
                    w_data <= rs2;
                end
        endcase
    end
    endtask

    task WriteBack;
    begin
        d_load <= 1'b1;
        wen <= 1'b1;
        casez(inst)
            `LW     :   register[rd_addr] <= d_mem_data;
            `ADD    :   register[rd_addr] <= alu_out;
            `SUB    :   register[rd_addr] <= alu_out;
            `ADDI   :   register[rd_addr] <= alu_out;
            `AND    :   register[rd_addr] <= alu_out;
            `OR     :   register[rd_addr] <= alu_out;
            `XOR    :   register[rd_addr] <= alu_out;
            `ANDI   :   register[rd_addr] <= alu_out;
            `ORI    :   register[rd_addr] <= alu_out;
            `XORI   :   register[rd_addr] <= alu_out;
        endcase
    end
    endtask


endmodule

src/startup.v
`timescale 1ns/1ps
`include "cpu/core.v"

module startup;

    parameter step = 10;
    parameter ticks = 40;

    reg clk;
    reg rst;

    Core core(
        .clk(clk),
        .rst(rst)
        );

    initial
        begin
            $dumpfile("wave.vcd");
            $dumpvars(0,core);
            $monitor("pc");
        end

    initial
        begin
            clk = 1'b1;
            forever
                begin
                    #(step/2) clk = !clk;
                end
        end

    initial
        begin
            rst = 1'b0;
            repeat (1) @(posedge clk) rst <= 1'b1;
            @(posedge clk) rst <= 1'b0;
        end

    initial
       begin
           repeat (ticks) @(posedge clk);
           $finish;
       end

endmodule

src/wave.vcd
$date
	Thu Aug  3 05:13:57 2023
$end
$version
	Icarus Verilog
$end
$timescale
	1ps
$end
$scope module startup $end
$scope module core $end
$var wire 1 ! clk $end
$var wire 1 " rst $end
$var wire 32 # mem_data [31:0] $end
$var wire 32 $ d_mem_data [31:0] $end
$var reg 32 % addr [31:0] $end
$var reg 32 & alu_out [31:0] $end
$var reg 32 ' d_addr [31:0] $end
$var reg 1 ( d_load $end
$var reg 13 ) imm_i [12:0] $end
$var reg 32 * imm_i_sext [31:0] $end
$var reg 13 + imm_s [12:0] $end
$var reg 32 , imm_s_sext [31:0] $end
$var reg 32 - inst [31:0] $end
$var reg 1 . load $end
$var reg 32 / pc [31:0] $end
$var reg 32 0 rd [31:0] $end
$var reg 5 1 rd_addr [4:0] $end
$var reg 32 2 rs1 [31:0] $end
$var reg 5 3 rs1_addr [4:0] $end
$var reg 32 4 rs2 [31:0] $end
$var reg 5 5 rs2_addr [4:0] $end
$var reg 3 6 stage [2:0] $end
$var reg 32 7 w_data [31:0] $end
$var reg 1 8 wen $end
$var integer 32 9 i [31:0] $end
$scope module memory $end
$var wire 32 : addr [31:0] $end
$var wire 32 ; d_addr [31:0] $end
$var wire 1 ( d_load $end
$var wire 1 . load $end
$var wire 32 < w_data [31:0] $end
$var wire 1 8 wen $end
$var reg 32 = d_data [31:0] $end
$var reg 32 > data [31:0] $end
$upscope $end
$scope task Excution $end
$upscope $end
$scope task IntructionDecode $end
$upscope $end
$scope task IntructionFetch $end
$upscope $end
$scope task MemoryAccess $end
$upscope $end
$scope task WriteBack $end
$upscope $end
$upscope $end
$upscope $end
$scope module startup $end
$scope module core $end
$var reg 32 ? \register[0] [31:0] $end
$upscope $end
$upscope $end
$scope module startup $end
$scope module core $end
$var reg 32 @ \register[1] [31:0] $end
$upscope $end
$upscope $end
$scope module startup $end
$scope module core $end
$var reg 32 A \register[2] [31:0] $end
$upscope $end
$upscope $end
$scope module startup $end
$scope module core $end
$var reg 32 B \register[3] [31:0] $end
$upscope $end
$upscope $end
$scope module startup $end
$scope module core $end
$var reg 32 C \register[4] [31:0] $end
$upscope $end
$upscope $end
$scope module startup $end
$scope module core $end
$var reg 32 D \register[5] [31:0] $end
$upscope $end
$upscope $end
$scope module startup $end
$scope module core $end
$var reg 32 E \register[6] [31:0] $end
$upscope $end
$upscope $end
$scope module startup $end
$scope module core $end
$var reg 32 F \register[7] [31:0] $end
$upscope $end
$upscope $end
$scope module startup $end
$scope module core $end
$scope module memory $end
$var reg 8 G \m[0] [7:0] $end
$upscope $end
$upscope $end
$upscope $end
$scope module startup $end
$scope module core $end
$scope module memory $end
$var reg 8 H \m[1] [7:0] $end
$upscope $end
$upscope $end
$upscope $end
$scope module startup $end
$scope module core $end
$scope module memory $end
$var reg 8 I \m[2] [7:0] $end
$upscope $end
$upscope $end
$upscope $end
$scope module startup $end
$scope module core $end
$scope module memory $end
$var reg 8 J \m[3] [7:0] $end
$upscope $end
$upscope $end
$upscope $end
$scope module startup $end
$scope module core $end
$scope module memory $end
$var reg 8 K \m[4] [7:0] $end
$upscope $end
$upscope $end
$upscope $end
$scope module startup $end
$scope module core $end
$scope module memory $end
$var reg 8 L \m[5] [7:0] $end
$upscope $end
$upscope $end
$upscope $end
$scope module startup $end
$scope module core $end
$scope module memory $end
$var reg 8 M \m[6] [7:0] $end
$upscope $end
$upscope $end
$upscope $end
$scope module startup $end
$scope module core $end
$scope module memory $end
$var reg 8 N \m[7] [7:0] $end
$upscope $end
$upscope $end
$upscope $end
$scope module startup $end
$scope module core $end
$scope module memory $end
$var reg 8 O \m[8] [7:0] $end
$upscope $end
$upscope $end
$upscope $end
$scope module startup $end
$scope module core $end
$scope module memory $end
$var reg 8 P \m[9] [7:0] $end
$upscope $end
$upscope $end
$upscope $end
$scope module startup $end
$scope module core $end
$scope module memory $end
$var reg 8 Q \m[10] [7:0] $end
$upscope $end
$upscope $end
$upscope $end
$scope module startup $end
$scope module core $end
$scope module memory $end
$var reg 8 R \m[11] [7:0] $end
$upscope $end
$upscope $end
$upscope $end
$scope module startup $end
$scope module core $end
$scope module memory $end
$var reg 8 S \m[12] [7:0] $end
$upscope $end
$upscope $end
$upscope $end
$scope module startup $end
$scope module core $end
$scope module memory $end
$var reg 8 T \m[13] [7:0] $end
$upscope $end
$upscope $end
$upscope $end
$scope module startup $end
$scope module core $end
$scope module memory $end
$var reg 8 U \m[14] [7:0] $end
$upscope $end
$upscope $end
$upscope $end
$scope module startup $end
$scope module core $end
$scope module memory $end
$var reg 8 V \m[15] [7:0] $end
$upscope $end
$upscope $end
$upscope $end
$scope module startup $end
$scope module core $end
$scope module memory $end
$var reg 8 W \m[16] [7:0] $end
$upscope $end
$upscope $end
$upscope $end
$scope module startup $end
$scope module core $end
$scope module memory $end
$var reg 8 X \m[17] [7:0] $end
$upscope $end
$upscope $end
$upscope $end
$scope module startup $end
$scope module core $end
$scope module memory $end
$var reg 8 Y \m[18] [7:0] $end
$upscope $end
$upscope $end
$upscope $end
$scope module startup $end
$scope module core $end
$scope module memory $end
$var reg 8 Z \m[19] [7:0] $end
$upscope $end
$upscope $end
$upscope $end
$scope module startup $end
$scope module core $end
$scope module memory $end
$var reg 8 [ \m[20] [7:0] $end
$upscope $end
$upscope $end
$upscope $end
$scope module startup $end
$scope module core $end
$scope module memory $end
$var reg 8 \ \m[21] [7:0] $end
$upscope $end
$upscope $end
$upscope $end
$scope module startup $end
$scope module core $end
$scope module memory $end
$var reg 8 ] \m[22] [7:0] $end
$upscope $end
$upscope $end
$upscope $end
$scope module startup $end
$scope module core $end
$scope module memory $end
$var reg 8 ^ \m[23] [7:0] $end
$upscope $end
$upscope $end
$upscope $end
$scope module startup $end
$scope module core $end
$scope module memory $end
$var reg 8 _ \m[24] [7:0] $end
$upscope $end
$upscope $end
$upscope $end
$scope module startup $end
$scope module core $end
$scope module memory $end
$var reg 8 ` \m[25] [7:0] $end
$upscope $end
$upscope $end
$upscope $end
$scope module startup $end
$scope module core $end
$scope module memory $end
$var reg 8 a \m[26] [7:0] $end
$upscope $end
$upscope $end
$upscope $end
$scope module startup $end
$scope module core $end
$scope module memory $end
$var reg 8 b \m[27] [7:0] $end
$upscope $end
$upscope $end
$upscope $end
$scope module startup $end
$scope module core $end
$scope module memory $end
$var reg 8 c \m[28] [7:0] $end
$upscope $end
$upscope $end
$upscope $end
$scope module startup $end
$scope module core $end
$scope module memory $end
$var reg 8 d \m[29] [7:0] $end
$upscope $end
$upscope $end
$upscope $end
$scope module startup $end
$scope module core $end
$scope module memory $end
$var reg 8 e \m[30] [7:0] $end
$upscope $end
$upscope $end
$upscope $end
$scope module startup $end
$scope module core $end
$scope module memory $end
$var reg 8 f \m[31] [7:0] $end
$upscope $end
$upscope $end
$upscope $end
$enddefinitions $end
#0
$dumpvars
bx f
bx e
bx d
bx c
bx b
bx a
bx `
bx _
bx ^
bx ]
bx \
bx [
bx Z
bx Y
bx X
bx W
bx V
bx U
bx T
bx S
bx R
bx Q
bx P
bx O
b0 N
b100000 M
b10000010 L
b110011 K
b1000000 J
b10001 I
b1 H
b10110011 G
b111 F
b110 E
b101 D
b100 C
b11 B
b10 A
b1 @
b0 ?
bx >
bx =
b0 <
bx ;
b0 :
b100000 9
18
b0 7
bx 6
b0 5
bx 4
b0 3
bx 2
b0 1
bx 0
bx /
1.
b1000000000100010000000110110011 -
bx ,
bx +
bx *
bx )
1(
bx '
bx &
b0 %
bx $
bx #
0"
1!
$end
#5000
0!
#10000
1"
1!
#15000
0!
#20000
b0 6
b0 /
0"
1!
#25000
0!
#30000
b1000000000100010000000110110011 #
b1000000000100010000000110110011 >
0.
b100 /
b1 6
1!
#35000
0!
#40000
b11 0
b1 4
b10 2
b10000000011 ,
b10000000001 *
b10000000011 +
b10000000001 )
b11 1
b1 5
b10 3
1.
b10 6
1!
#45000
0!
#50000
b1 &
b11 6
1!
#55000
0!
#60000
b100 6
1!
#65000
0!
#70000
b1 B
b0 6
1!
#75000
0!
#80000
b1000001000001000110011 #
b1000001000001000110011 >
0.
b100 %
b100 :
b1000 /
b1 6
1!
#85000
0!
#90000
b100 0
b10 4
b1 2
b100 ,
b10 *
b100 +
b10 )
b100 1
b10 5
b1 3
1.
b1000001000001000110011 -
b10 6
1!
#95000
0!
#100000
b11 &
b11 6
1!
#105000
0!
#110000
b100 6
1!
#115000
0!
#120000
b11 C
b0 6
1!
#125000
0!
#130000
bx #
bx >
0.
b1000 %
b1000 :
b1100 /
b1 6
1!
#135000
0!
#140000
bx 0
bx 4
bx 2
bx ,
bx *
b0xxxxxxxxxxxx +
b0xxxxxxxxxxxx )
bx 1
bx 5
bx 3
1.
bx -
b10 6
1!
#145000
0!
#150000
b11 6
1!
#155000
0!
#160000
b100 6
1!
#165000
0!
#170000
b0 6
1!
#175000
0!
#180000
0.
b1100 %
b1100 :
b10000 /
b1 6
1!
#185000
0!
#190000
1.
b10 6
1!
#195000
0!
#200000
b11 6
1!
#205000
0!
#210000
b100 6
1!
#215000
0!
#220000
b0 6
1!
#225000
0!
#230000
0.
b10000 %
b10000 :
b10100 /
b1 6
1!
#235000
0!
#240000
1.
b10 6
1!
#245000
0!
#250000
b11 6
1!
#255000
0!
#260000
b100 6
1!
#265000
0!
#270000
b0 6
1!
#275000
0!
#280000
0.
b10100 %
b10100 :
b11000 /
b1 6
1!
#285000
0!
#290000
1.
b10 6
1!
#295000
0!
#300000
b11 6
1!
#305000
0!
#310000
b100 6
1!
#315000
0!
#320000
b0 6
1!
#325000
0!
#330000
0.
b11000 %
b11000 :
b11100 /
b1 6
1!
#335000
0!
#340000
1.
b10 6
1!
#345000
0!
#350000
b11 6
1!
#355000
0!
#360000
b100 6
1!
#365000
0!
#370000
b0 6
1!
#375000
0!
#380000
0.
b11100 %
b11100 :
b100000 /
b1 6
1!
#385000
0!
#390000
1.
b10 6
1!
#395000
0!
#400000
b11 6
1!
